Metadata-Version: 1.0
Name: distributions-exer
Version: 0.2
Summary: General, Gaussian, and Binomial distributions
Home-page: UNKNOWN
Author: UNKNOWN
Author-email: UNKNOWN
License: UNKNOWN
Platform: UNKNOWN
